isikukood/__init__.py
isikukood/assertions.py
isikukood/errors.py
isikukood/functions.py
isikukood/isikukood.py
isikukood-1.0.2.dist-info/LICENSE
isikukood-1.0.2.dist-info/METADATA
isikukood-1.0.2.dist-info/WHEEL
isikukood-1.0.2.dist-info/top_level.txt
isikukood-1.0.2.dist-info/RECORD
