Metadata-Version: 2.1
Name: isikukood
Version: 1.0.2
Summary: Estonian SSN library
Home-page: https://github.com/ui-1/isikukood
Author: ui-1
Author-email: ui-1@posteo.org
License: GPLv3
Classifier: Development Status :: 5 - Production/Stable
Classifier: Intended Audience :: Developers
Classifier: License :: OSI Approved :: GNU General Public License v3 (GPLv3)
Classifier: Natural Language :: English
Classifier: Programming Language :: Python
Classifier: Programming Language :: Python :: 3
Classifier: Programming Language :: Python :: 3.7
Classifier: Operating System :: OS Independent
Classifier: Topic :: Software Development :: Libraries
License-File: LICENSE
Requires-Dist: multimethod
